[{
    "id": 1,
    "name": "P-1",
    "owner": "Amy",
    "latestChange": 1573858343,
    "techData": {
        "roles":[
            {"name":"Di", "permission": ["Edit", "Delete"]},
            {"name":"Wo", "permission": ["Edit", "Delete"]},
            {"name":"Wed", "permission": ["Edit", "Delete"]},
            {"name":"Do", "permission": ["Edit", "Update"]},
            {"name":"Sa", "permission": ["Edit", "Delete"]},
            {"name":"Son", "permission": ["Edit", "Delete"]},
            {"name":"Li", "permission": ["Edit", "Delete"]}
        ]
        },
        "metaData": {
            "configManager": "Amy",
            "name": "T_1",
            "owner": "David"
        }
},
{
    "id": 2,
    "name": "P-2",
    "owner": "Ronaldo",
    "latestChange": 1573858343,
    "techData": {
        "roles":[
            {"name":"Di", "permission": ["Edit", "Delete"]},
            {"name":"Wo", "permission": ["Edit", "Delete"]},
            {"name":"Wed", "permission": ["Edit", "Delete"]},
            {"name":"Do", "permission": ["Edit", "Update"]},
            {"name":"Sa", "permission": ["Edit", "Delete"]},
            {"name":"Son", "permission": ["Edit", "Delete"]},
            {"name":"Li", "permission": ["Edit", "Delete"]}
        ]
        },
        "metaData": {
            "configManager": "Amy",
            "name": "T_1",
            "owner": "David"
        }
},
{
    "id": 3,
    "name": "P-3",
    "owner": "Tim",
    "latestChange": 1573858343,
    "techData": {
        "roles":[
            {"name":"Di", "permission": ["Edit", "Delete"]},
            {"name":"Wo", "permission": ["Edit", "Delete"]},
            {"name":"Wed", "permission": ["Edit", "Delete"]},
            {"name":"Do", "permission": ["Edit", "Update"]},
            {"name":"Sa", "permission": ["Edit", "Delete"]},
            {"name":"Son", "permission": ["Edit", "Delete"]},
            {"name":"Li", "permission": ["Edit", "Delete"]}
        ]
        },
        "metaData": {
            "configManager": "Amy",
            "name": "T_1",
            "owner": "David"
        }
},
{
    "id": 4,
    "name": "P-4",
    "owner": "Kyky",
    "latestChange": 1573858343,
    "techData": {
        "roles":[
            {"name":"Di", "permission": ["Edit", "Delete"]},
            {"name":"Wo", "permission": ["Edit", "Delete"]},
            {"name":"Wed", "permission": ["Edit", "Delete"]},
            {"name":"Do", "permission": ["Edit", "Update"]},
            {"name":"Sa", "permission": ["Edit", "Delete"]},
            {"name":"Son", "permission": ["Edit", "Delete"]},
            {"name":"Li", "permission": ["Edit", "Delete"]}
        ]
        },
        "metaData": {
            "configManager": "Amy",
            "name": "T_1",
            "owner": "David"
        }
},
{
    "id": 5,
    "name": "P-5",
    "owner": "Opa",
    "latestChange": 1573858343,
    "techData": {
        "roles":[
            {"name":"Di", "permission": ["Edit", "Delete"]},
            {"name":"Wo", "permission": ["Edit", "Delete"]},
            {"name":"Wed", "permission": ["Edit", "Delete"]},
            {"name":"Do", "permission": ["Edit", "Update"]},
            {"name":"Sa", "permission": ["Edit", "Delete"]},
            {"name":"Son", "permission": ["Edit", "Delete"]},
            {"name":"Li", "permission": ["Edit", "Delete"]}
        ]
        },
        "metaData": {
            "configManager": "Amy",
            "name": "T_1",
            "owner": "David"
        }
},
{
    "id": 6,
    "name": "P-6",
    "owner": "Xeon",
    "latestChange": 1573858343,
    "techData": {
        "roles":[
            {"name":"Di", "permission": ["Edit", "Delete"]},
            {"name":"Wo", "permission": ["Edit", "Delete"]},
            {"name":"Wed", "permission": ["Edit", "Delete"]},
            {"name":"Do", "permission": ["Edit", "Update"]},
            {"name":"Sa", "permission": ["Edit", "Delete"]},
            {"name":"Son", "permission": ["Edit", "Delete"]},
            {"name":"Li", "permission": ["Edit", "Delete"]}
        ]
        },
        "metaData": {
            "configManager": "Amy",
            "name": "T_1",
            "owner": "David"
        }
},
{
    "id": 7,
    "name": "P-7",
    "owner": "Leo",
    "latestChange": 1573858343,
    "techData": {
        "roles":[
            {"name":"Di", "permission": ["Edit", "Delete"]},
            {"name":"Wo", "permission": ["Edit", "Delete"]},
            {"name":"Wed", "permission": ["Edit", "Delete"]},
            {"name":"Do", "permission": ["Edit", "Update"]},
            {"name":"Sa", "permission": ["Edit", "Delete"]},
            {"name":"Son", "permission": ["Edit", "Delete"]},
            {"name":"Li", "permission": ["Edit", "Delete"]}
        ]
        },
        "metaData": {
            "configManager": "Amy",
            "name": "T_1",
            "owner": "David"
        }
},
{
    "id": 8,
    "name": "P-8",
    "owner": "Hassy",
    "latestChange": 1573858343,
    "techData": {
        "roles":[
            {"name":"Di", "permission": ["Edit", "Delete"]},
            {"name":"Wo", "permission": ["Edit", "Delete"]},
            {"name":"Wed", "permission": ["Edit", "Delete"]},
            {"name":"Do", "permission": ["Edit", "Update"]},
            {"name":"Sa", "permission": ["Edit", "Delete"]},
            {"name":"Son", "permission": ["Edit", "Delete"]},
            {"name":"Li", "permission": ["Edit", "Delete"]}
        ]
        },
        "metaData": {
            "configManager": "Amy",
            "name": "T_1",
            "owner": "David"
        }
}
]